notionlib/__init__.py
notionlib/notion.py
notionlib-0.3.dev0.dist-info/AUTHORS
notionlib-0.3.dev0.dist-info/LICENSE
notionlib-0.3.dev0.dist-info/METADATA
notionlib-0.3.dev0.dist-info/WHEEL
notionlib-0.3.dev0.dist-info/top_level.txt
notionlib-0.3.dev0.dist-info/RECORD
