Metadata-Version: 2.1
Name: notionlib
Version: 0.3.dev0
Summary: An unofficial Python 3 client for the Notion.so API
Home-page: https://github.com/jdhp/notion-lib
Download-URL: 
Author: Jérémie DECOCK
Author-email: jd.jdhp@gmail.com
Maintainer: Jérémie DECOCK
Maintainer-email: jd.jdhp@gmail.com
Project-URL: Bug Tracker, https://github.com/jdhp/notion-lib/issues
Keywords: Gitlab
Classifier: Development Status :: 4 - Beta
Classifier: Intended Audience :: Developers
Classifier: Natural Language :: English
Classifier: Operating System :: OS Independent
Classifier: Programming Language :: Python :: 3
Classifier: Topic :: Software Development :: Libraries
Classifier: Topic :: Software Development :: Libraries :: Python Modules
Classifier: Topic :: Software Development :: Libraries :: Application Frameworks
Requires-Python: >=3.6
License-File: LICENSE
License-File: AUTHORS
